adafruit_circuitpython_mcp3xxx-1.4.22.dist-info/licenses/LICENSE
adafruit_mcp3xxx/__init__.py
adafruit_mcp3xxx/analog_in.py
adafruit_mcp3xxx/mcp3002.py
adafruit_mcp3xxx/mcp3004.py
adafruit_mcp3xxx/mcp3008.py
adafruit_mcp3xxx/mcp3xxx.py
adafruit_circuitpython_mcp3xxx-1.4.22.dist-info/METADATA
adafruit_circuitpython_mcp3xxx-1.4.22.dist-info/WHEEL
adafruit_circuitpython_mcp3xxx-1.4.22.dist-info/top_level.txt
adafruit_circuitpython_mcp3xxx-1.4.22.dist-info/RECORD
